[
 {
  "id": "nai-o-lkoni",
  "page": 494,
  "section_en": "Liqueurs",
  "title_it": "Nai 'Olkoni",
  "title_en": "Nai 'Olkoni",
  "method": "cold_mix",
  "yield": {
   "amount": 10,
   "unit": "litres",
   "note": "alcohol 30%"
  },
  "alcohol_strength": {
   "degrees": 30,
   "raw": "alcool 30%"
  },
  "ingredients": [
   {
    "name_it": "Olio essenz. di limono",
    "name_en": "Lemon essential oil",
    "qty": null,
    "unit": "grams",
    "unit_implicit": true,
    "note": "quantity unclear from OCR"
   },
   {
    "name_it": "Olio essenz. di coriandoli",
    "name_en": "Coriander essential oil",
    "qty": 1,
    "unit": "grams",
    "unit_implicit": true
   },
   {
    "name_it": "Olio essenz. di garofani",
    "name_en": "Clove essential oil",
    "qty": 24,
    "unit": "drops",
    "unit_implicit": false
   },
   {
    "name_it": "Olio essenz. di macis",
    "name_en": "Mace essential oil",
    "qty": 12,
    "unit": "drops",
    "unit_implicit": false
   },
   {
    "name_it": "Olio essenz. di cannella",
    "name_en": "Cinnamon essential oil",
    "qty": 10,
    "unit": "drops",
    "unit_implicit": false
   },
   {
    "name_it": "Olio essenz. di rose sublime",
    "name_en": "Sublime rose essential oil",
    "qty": 2,
    "unit": "drops",
    "unit_implicit": false
   },
   {
    "name_it": "Tintura di vaniglia",
    "name_en": "Vanilla tincture",
    "qty": 5,
    "unit": "grams",
    "unit_implicit": false
   },
   {
    "name_it": "Alcool di 90°",
    "name_en": "Alcohol 90°",
    "qty": 4,
    "unit": "litres",
    "unit_implicit": false
   },
   {
    "name_it": "Zucchero",
    "name_en": "Sugar",
    "qty": 2200,
    "unit": "grams",
    "unit_implicit": true
   },
   {
    "name_it": "Acqua",
    "name_en": "Water",
    "qty": 4750,
    "unit": "millilitres",
    "unit_implicit": true
   },
   {
    "name_it": "Colore azzurro o rosso",
    "name_en": "Blue or red colouring",
    "qty": null,
    "unit": "q.b.",
    "unit_implicit": false,
    "note": "to taste"
   }
  ],
  "steps_en": [
   "Mix essential oils and tincture.",
   "Add alcohol.",
   "Dissolve sugar in water.",
   "Combine sugar solution with spirit mixture.",
   "Add colouring to taste."
  ],
  "notes_en": "Final product yields 10 litres at 30% alcohol strength.",
  "confidence": 0.7
 },
 {
  "id": "noccioli-di-phalsburg-crema",
  "page": 494,
  "section_en": "Liqueurs",
  "title_it": "Noccioli di Phalsburg (Crema)",
  "title_en": "Hazelnuts of Phalsburg (Cream)",
  "method": "cold_mix",
  "yield": null,
  "alcohol_strength": null,
  "ingredients": [
   {
    "name_it": "Olio essenz. di semi di pesco",
    "name_en": "Peach kernel essential oil",
    "qty": 5,
    "unit": "grams",
    "unit_implicit": false
   },
   {
    "name_it": "Olio essenz. di mandorle amare",
    "name_en": "Bitter almond essential oil",
    "qty": 1,
    "unit": "grams",
    "unit_implicit": false
   },
   {
    "name_it": "Olio essenz. di garofani",
    "name_en": "Clove essential oil",
    "qty": 0.2,
    "unit": "grams",
    "unit_implicit": false
   },
   {
    "name_it": "Olio essenz. di cannella",
    "name_en": "Cinnamon essential oil",
    "qty": 0.4,
    "unit": "grams",
    "unit_implicit": false
   },
   {
    "name_it": "Olio essenz. di fiori d'arancio",
    "name_en": "Orange flower essential oil",
    "qty": 0.2,
    "unit": "grams",
    "unit_implicit": false
   },
   {
    "name_it": "Olio essenz. di arancio",
    "name_en": "Orange essential oil",
    "qty": 1,
    "unit": "grams",
    "unit_implicit": false
   },
   {
    "name_it": "Olio essenz. di limono",
    "name_en": "Lemon essential oil",
    "qty": 0.8,
    "unit": "grams",
    "unit_implicit": false
   },
   {
    "name_it": "Olio essenz. di noce moscata",
    "name_en": "Nutmeg essential oil",
    "qty": 0.1,
    "unit": "grams",
    "unit_implicit": false
   },
   {
    "name_it": "Alcool di 85°",
    "name_en": "Alcohol 85°",
    "qty": 4,
    "unit": "litres",
    "unit_implicit": false
   },
   {
    "name_it": "Zucchero",
    "name_en": "Sugar",
    "qty": 5,
    "unit": "kilograms",
    "unit_implicit": false
   },
   {
    "name_it": "Acqua",
    "name_en": "Water",
    "qty": 2.6,
    "unit": "litres",
    "unit_implicit": false
   }
  ],
  "steps_en": [
   "Combine all essential oils.",
   "Mix with alcohol.",
   "Dissolve sugar in water.",
   "Combine sugar solution with spirit mixture."
  ],
  "confidence": 0.8
 },
 {
  "id": "obohonskaya-liqueur",
  "page": 494,
  "section_en": "Liqueurs",
  "title_it": "Obohonskaya (Liquore matto)",
  "title_en": "Obohonskaya (Crazy Liqueur)",
  "method": "cold_mix",
  "yield": null,
  "alcohol_strength": null,
  "ingredients": [
   {
    "name_it": "Olio essenz. di calamo",
    "name_en": "Calamus essential oil",
    "qty": 3.5,
    "unit": "grams",
    "unit_implicit": false
   },
   {
    "name_it": "Olio essenz. di zenzero",
    "name_en": "Ginger essential oil",
    "qty": 1.8,
    "unit": "grams",
    "unit_implicit": false
   },
   {
    "name_it": "Olio essenz. di ginepro (bacche)",
    "name_en": "Juniper (berries) essential oil",
    "qty": 1.8,
    "unit": "grams",
    "unit_implicit": false
   },
   {
    "name_it": "Essenza per acqua Danzica",
    "name_en": "Danzig water essence (p. 239)",
    "qty": 4,
    "unit": "grams",
    "unit_implicit": false,
    "note": "see page 239"
   },
   {
    "name_it": "Alcool di 90°",
    "name_en": "Alcohol 90°",
    "qty": 10,
    "unit": "litres",
    "unit_implicit": false
   },
   {
    "name_it": "Sciroppo",
    "name_en": "Syrup",
    "qty": null,
    "unit": "unit",
    "unit_implicit": true,
    "note": "quantity unclear from OCR"
   },
   {
    "name_it": "Acqua",
    "name_en": "Water",
    "qty": null,
    "unit": "unit",
    "unit_implicit": true,
    "note": "quantity unclear from OCR"
   }
  ],
  "steps_en": [
   "Mix essential oils with Danzig water essence.",
   "Combine with alcohol.",
   "Add syrup and water to desired strength and sweetness."
  ],
  "notes_en": "Syrup and water quantities are illegible in the source.",
  "ocr_flags": [
   "Obohonskaya spelling uncertain",
   "syrup and water quantities unreadable"
  ],
  "confidence": 0.65
 },
 {
  "id": "punch-no-1-and-2",
  "page": 494,
  "section_en": "Punches",
  "title_it": "Punch no. I e II",
  "title_en": "Punch no. I and II",
  "method": "cold_mix",
  "yield": null,
  "alcohol_strength": null,
  "ingredients": [
   {
    "name_it": "Olio essenz. di mandorlo amaro",
    "name_en": "Bitter almond essential oil",
    "qty": 2.5,
    "unit": "grams",
    "unit_implicit": false,
    "variants": [
     5
    ]
   },
   {
    "name_it": "Olio essenz. di cardamomo",
    "name_en": "Cardamom essential oil",
    "qty": null,
    "unit": "drops",
    "unit_implicit": false,
    "variants": [
     null
    ],
    "note": "4 drops in recipe I; quantity in recipe II unclear from OCR"
   },
   {
    "name_it": "Olio essenz. di limoni",
    "name_en": "Lemon essential oil",
    "qty": null,
    "unit": "drops",
    "unit_implicit": false,
    "variants": [
     null
    ],
    "note": "4 drops in recipe I; quantity in recipe II unclear from OCR"
   },
   {
    "name_it": "Olio essenz. di fiori d'arancio",
    "name_en": "Orange flower essential oil",
    "qty": null,
    "unit": "drops",
    "unit_implicit": false,
    "variants": [
     null
    ],
    "note": "2 drops in recipe I; quantity in recipe II unclear from OCR"
   },
   {
    "name_it": "Alcool di 90°",
    "name_en": "Alcohol 90°",
    "qty": 4,
    "unit": "litres",
    "unit_implicit": false,
    "variants": [
     4
    ]
   }
  ],
  "steps_en": [
   "Mix essential oils.",
   "Add alcohol to the specified volume."
  ],
  "notes_en": "This entry presents two variations (Punch no. I and II). Recipe II proportions are partially unreadable from OCR degradation.",
  "ocr_flags": [
   "cardamom drops qty in recipe II unreadable",
   "lemon drops qty in recipe II unreadable",
   "orange flower drops qty in recipe II unreadable"
  ],
  "confidence": 0.6
 }
]